xlaz/__init__.py
xlaz/hlo_lexer.py
xlaz/pb/__init__.py
xlaz/pb/tensorflow/compiler/xla/service/hlo_pb2.py
xlaz/pb/tensorflow/compiler/xla/xla_data_pb2.py
xlaz/pb/tensorflow/compiler/xla/xla_pb2.py
xlaz/primitive_util.py
xlaz-0.7.0.dist-info/LICENSE
xlaz-0.7.0.dist-info/WHEEL
xlaz-0.7.0.dist-info/METADATA
xlaz-0.7.0.dist-info/RECORD
