Metadata-Version: 2.1
Name: xlaz
Version: 0.7.0
Summary: XLA utilities in pure Python
Home-page: https://github.com/shawwn/xlaz
License: MIT
Author: Shawn Presser
Author-email: shawnpresser@gmail.com
Requires-Python: >=3.8,<4.0
Classifier: License :: OSI Approved :: MIT License
Classifier: Programming Language :: Python :: 3
Classifier: Programming Language :: Python :: 3.8
Classifier: Programming Language :: Python :: 3.9
Classifier: Programming Language :: Python :: 3.10
Requires-Dist: tensorflow-checkpoint-reader (>=0.1.2,<0.2.0)
